mwahpy/__init__.py
mwahpy/coords.py
mwahpy/data.py
mwahpy/flags.py
mwahpy/histogram.py
mwahpy/mwah_data.py
mwahpy/mwah_handle_output.py
mwahpy/mwahplot.py
mwahpy/mwahpy.py
mwahpy/mwahpy_glob.py
mwahpy/mwahpy_global.py
mwahpy/mwahpy_plotting.py
mwahpy/nbody.py
mwahpy/orbit_fitter.py
mwahpy/orbit_fitter_gc.py
mwahpy/orbit_fitting.py
mwahpy/orbit_fitting_gc.py
mwahpy/output_handler.py
mwahpy/plot.py
mwahpy/pot.py
mwahpy/test.py
mwahpy/timestep.py
mwahpy/__pycache__/__init__.cpython-36.pyc
mwahpy/__pycache__/__init__.cpython-38.pyc
mwahpy/__pycache__/coords.cpython-35.pyc
mwahpy/__pycache__/coords.cpython-36.pyc
mwahpy/__pycache__/coords.cpython-38.pyc
mwahpy/__pycache__/data.cpython-35.pyc
mwahpy/__pycache__/data.cpython-36.pyc
mwahpy/__pycache__/flags.cpython-35.pyc
mwahpy/__pycache__/flags.cpython-36.pyc
mwahpy/__pycache__/flags.cpython-38.pyc
mwahpy/__pycache__/glob.cpython-35.pyc
mwahpy/__pycache__/mwahpy_glob.cpython-35.pyc
mwahpy/__pycache__/mwahpy_glob.cpython-36.pyc
mwahpy/__pycache__/mwahpy_glob.cpython-38.pyc
mwahpy/__pycache__/mwahpy_global.cpython-35.pyc
mwahpy/__pycache__/nbody.cpython-36.pyc
mwahpy/__pycache__/nbody.cpython-38.pyc
mwahpy/__pycache__/orbit_fitter.cpython-36.pyc
mwahpy/__pycache__/orbit_fitter.cpython-38.pyc
mwahpy/__pycache__/orbit_fitter_gc.cpython-36.pyc
mwahpy/__pycache__/orbit_fitting.cpython-36.pyc
mwahpy/__pycache__/orbit_fitting_gc.cpython-36.pyc
mwahpy/__pycache__/orbit_fitting_gc_new.cpython-36.pyc
mwahpy/__pycache__/output_handler.cpython-35.pyc
mwahpy/__pycache__/output_handler.cpython-36.pyc
mwahpy/__pycache__/output_handler.cpython-38.pyc
mwahpy/__pycache__/plot.cpython-36.pyc
mwahpy/__pycache__/plot.cpython-38.pyc
mwahpy/__pycache__/pot.cpython-35.pyc
mwahpy/__pycache__/pot.cpython-36.pyc
mwahpy/__pycache__/pot.cpython-38.pyc
mwahpy/__pycache__/timestep.cpython-36.pyc
mwahpy/__pycache__/timestep.cpython-38.pyc
mwahpy_tests/__init__.py
mwahpy_tests/test.py
mwahpy_tests/test_bodies.out
mwahpy_tests/nbody_test/1
mwahpy-2.1.2.dist-info/LICENSE.txt
mwahpy-2.1.2.dist-info/METADATA
mwahpy-2.1.2.dist-info/WHEEL
mwahpy-2.1.2.dist-info/top_level.txt
mwahpy-2.1.2.dist-info/RECORD
