Metadata-Version: 2.1
Name: mwahpy
Version: 2.1.2
Summary: A python package for easily parsing and processing data from MilkyWay@home
Home-page: https://github.com/thomasdonlon/mwahpy
Author: Tom Donlon
Author-email: donlot@rpi.edu
Classifier: Programming Language :: Python :: 3
Classifier: License :: OSI Approved :: MIT License
Classifier: Operating System :: OS Independent
Requires-Python: >=3.6.0
License-File: LICENSE.txt
Requires-Dist: numpy
Requires-Dist: galpy
Requires-Dist: matplotlib
Requires-Dist: astropy
Requires-Dist: scipy
Requires-Dist: pandas
